gfxls.py
gfxls-0.2.0.dist-info/METADATA
gfxls-0.2.0.dist-info/WHEEL
gfxls-0.2.0.dist-info/entry_points.txt
gfxls-0.2.0.dist-info/licenses/LICENSE
gfxls-0.2.0.dist-info/RECORD
