Metadata-Version: 2.1
Name: gfxls
Version: 0.2.0
Summary: gfxls - list files on terminal with thumbnails
Project-URL: Homepage, https://gitlab.com/hydrargyrum/gfxls
License-Expression: MIT
License-File: LICENSE
Keywords: color,filebrowser,image,ls,terminal
Classifier: Development Status :: 4 - Beta
Classifier: Intended Audience :: Developers
Classifier: License :: Public Domain
Classifier: Programming Language :: Python :: 3
Classifier: Programming Language :: Python :: 3.7
Classifier: Programming Language :: Python :: 3.8
Classifier: Programming Language :: Python :: 3.9
Classifier: Programming Language :: Python :: 3.10
Classifier: Programming Language :: Python :: 3.11
Classifier: Topic :: Desktop Environment
Classifier: Topic :: Multimedia :: Graphics
Classifier: Topic :: Software Development :: Libraries :: Python Modules
Classifier: Topic :: Utilities
Requires-Python: >=3
Requires-Dist: pillow
Requires-Dist: prettytable
Requires-Dist: vignette
